folium_pmtiles/__init__.py
folium_pmtiles/raster.py
folium_pmtiles/vector.py
folium_pmtiles-0.4.3.dist-info/LICENSE
folium_pmtiles-0.4.3.dist-info/METADATA
folium_pmtiles-0.4.3.dist-info/WHEEL
folium_pmtiles-0.4.3.dist-info/RECORD
