Metadata-Version: 2.1
Name: folium-pmtiles
Version: 0.4.3
Summary: Folium Plugin to Support PMTiles
Home-page: https://github.com/jtmiclat/folium-pmtiles
License: MIT
Author: Jt Miclat
Author-email: jtmiclat@gmail.com
Requires-Python: >=3.8,<4.0
Classifier: License :: OSI Approved :: MIT License
Classifier: Programming Language :: Python :: 3
Classifier: Programming Language :: Python :: 3.8
Classifier: Programming Language :: Python :: 3.9
Classifier: Programming Language :: Python :: 3.10
Classifier: Programming Language :: Python :: 3.11
Classifier: Programming Language :: Python :: 3.12
Classifier: Topic :: Scientific/Engineering :: GIS
Classifier: Topic :: Scientific/Engineering :: Visualization
Requires-Dist: folium (>=0.14.0)
Project-URL: Repository, https://github.com/jtmiclat/folium-pmtiles
